nifi/__init__.py
nifi/flowfile/__init__.py
nifi/flowfile/__main__.py
nifi/flowfile/_version.py
nifi/flowfile/attributes.py
nifi/flowfile/cli.py
nifi/flowfile/flowfile.py
nifi/flowfile/stream.py
nifi/sqs_workers/__init__.py
nifi/sqs_workers/codec.py
nifi/sqs_workers/processor.py
nifi/sqs_workers/queue.py
nifi.flowfile-0.0.2.dist-info/LICENSE
nifi.flowfile-0.0.2.dist-info/METADATA
nifi.flowfile-0.0.2.dist-info/WHEEL
nifi.flowfile-0.0.2.dist-info/entry_points.txt
nifi.flowfile-0.0.2.dist-info/top_level.txt
nifi.flowfile-0.0.2.dist-info/RECORD
