Metadata-Version: 2.1
Name: nifi.flowfile
Version: 0.0.2
Summary: NiFi FlowFile Serializer
Home-page: https://github.com/zeroae/nifi.flowfile
Author: Patrick Sodré
Author-email: patrick@zero-ae.com
License: Apache
Keywords: flowfile nifi
Platform: UNKNOWN
Classifier: Development Status :: 2 - Pre-Alpha
Classifier: Intended Audience :: Developers
Classifier: License :: OSI Approved :: Apache Software License
Classifier: Natural Language :: English
Classifier: Programming Language :: Python :: 3
Classifier: Programming Language :: Python :: 3.6
Classifier: Programming Language :: Python :: 3.7
Classifier: Programming Language :: Python :: 3.8
Requires-Python: >=3.6
Requires-Dist: click (>=7.0)
Requires-Dist: click-plugins
Requires-Dist: entrypoints
Requires-Dist: sqs-workers
Provides-Extra: doc
Requires-Dist: sphinx ; extra == 'doc'
Requires-Dist: sphinx-autoapi ; extra == 'doc'
Requires-Dist: sphinx-click ; extra == 'doc'
Requires-Dist: watchdog ; extra == 'doc'
Provides-Extra: test
Requires-Dist: pytest (>=3) ; extra == 'test'
Requires-Dist: pytest-cov ; extra == 'test'
